fs_monitor_mqtt/__init__.py
fs_monitor_mqtt/cli.py
fs_monitor_mqtt/fs_monitor.py
fs_monitor_mqtt/monitor.py
fs_monitor_mqtt/mqtt_client.py
fs_monitor_mqtt/utils.py
fs_monitor_mqtt-0.3.1.dist-info/LICENSE
fs_monitor_mqtt-0.3.1.dist-info/METADATA
fs_monitor_mqtt-0.3.1.dist-info/WHEEL
fs_monitor_mqtt-0.3.1.dist-info/entry_points.txt
fs_monitor_mqtt-0.3.1.dist-info/RECORD
