Metadata-Version: 2.1
Name: fs-monitor-mqtt
Version: 0.3.1
Summary: A file system monitor that can publish file change events to MQTT broker.
Home-page: https://github.com/likair/fs-monitor-mqtt
License: MIT
Keywords: filesystem,mqtt,monitor
Author: Likai Ren
Author-email: lebsfi@gmail.com
Requires-Python: >=3.9,<4.0
Classifier: License :: OSI Approved :: MIT License
Classifier: Programming Language :: Python :: 3
Classifier: Programming Language :: Python :: 3.9
Classifier: Programming Language :: Python :: 3.10
Classifier: Programming Language :: Python :: 3.11
Requires-Dist: paho-mqtt (>=1.6.1,<2.0.0)
Requires-Dist: typer (>=0.9.0,<0.10.0)
Requires-Dist: watchdog (>=3.0.0,<4.0.0)
Project-URL: Repository, https://github.com/likair/fs-monitor-mqtt
